{
  "run_id": "run-ab359d013451",
  "status": "completed",
  "config_path": "",
  "created_at": "2026-04-01T04:17:29+00:00",
  "updated_at": "2026-04-01T05:11:41+00:00",
  "stage_started_at": "2026-04-01T05:08:22+00:00",
  "stage_finished_at": "2026-04-01T05:11:41+00:00",
  "retry_count": 0,
  "note": "RocketReach enrichment completed with no sendable recruiter emails.",
  "last_error": "",
  "paths": {
    "run_dir": "D:\\Automation- Project\\pipeline\\runs\\run-ab359d013451",
    "applied_csv": "D:\\Automation- Project\\pipeline\\runs\\run-ab359d013451\\applied_jobs.csv",
    "recruiters_csv": "D:\\Automation- Project\\pipeline\\runs\\run-ab359d013451\\recruiters_enriched.csv",
    "send_report_csv": "D:\\Automation- Project\\pipeline\\reports\\run-ab359d013451.csv",
    "manifest_json": "D:\\Automation- Project\\pipeline\\meta\\run-ab359d013451.json",
    "logs_dir": "D:\\Automation- Project\\pipeline\\logs\\run-ab359d013451",
    "linkedin_stdout_log": "D:\\Automation- Project\\pipeline\\logs\\run-ab359d013451\\linkedin.stdout.log",
    "linkedin_stderr_log": "D:\\Automation- Project\\pipeline\\logs\\run-ab359d013451\\linkedin.stderr.log",
    "rocketreach_stdout_log": "D:\\Automation- Project\\pipeline\\logs\\run-ab359d013451\\rocketreach.stdout.log",
    "rocketreach_stderr_log": "D:\\Automation- Project\\pipeline\\logs\\run-ab359d013451\\rocketreach.stderr.log"
  },
  "artifacts": {
    "applied_csv_exists": false,
    "recruiters_csv_exists": false,
    "send_report_exists": false
  }
}